NewsAgent/__init__.py
NewsAgent/__main__.py
NewsAgent/agent.py
NewsAgent/destinations.py
NewsAgent/newsitems.py
NewsAgent/sources.py
NewsAgent-1.10.dist-info/LICENSE
NewsAgent-1.10.dist-info/METADATA
NewsAgent-1.10.dist-info/WHEEL
NewsAgent-1.10.dist-info/top_level.txt
NewsAgent-1.10.dist-info/RECORD
