Metadata-Version: 2.1
Name: NewsAgent
Version: 1.10
Summary: A News Agent
Home-page: https://github.com/pypa/sampleproject
Author: Allen
Author-email: allen.haha@hotmail.com
License: UNKNOWN
Platform: UNKNOWN
Classifier: Programming Language :: Python :: 3
Classifier: License :: OSI Approved :: MIT License
Classifier: Operating System :: OS Independent
